sqlalchemy_to_ormar/__init__.py
sqlalchemy_to_ormar/main.py
sqlalchemy_to_ormar/maps.py
sqlalchemy_to_ormar-0.0.2.data/data/LICENSE.md
sqlalchemy_to_ormar-0.0.2.dist-info/LICENSE.md
sqlalchemy_to_ormar-0.0.2.dist-info/METADATA
sqlalchemy_to_ormar-0.0.2.dist-info/WHEEL
sqlalchemy_to_ormar-0.0.2.dist-info/top_level.txt
sqlalchemy_to_ormar-0.0.2.dist-info/RECORD
