Metadata-Version: 2.1
Name: sqlalchemy-to-ormar
Version: 0.0.2
Summary: A simple auto-translator from sqlalchemy ORM models to ormar models.
Home-page: https://github.com/collerek/sqlalchemy-to-ormar
Author: Radosław Drążkiewicz
Author-email: collerek@gmail.com
License: MIT
Keywords: orm,sqlalchemy,ormar,databases,async,alembic
Platform: UNKNOWN
Classifier: Development Status :: 4 - Beta
Classifier: Environment :: Web Environment
Classifier: Intended Audience :: Developers
Classifier: License :: OSI Approved :: MIT License
Classifier: Operating System :: OS Independent
Classifier: Topic :: Internet :: WWW/HTTP
Classifier: Framework :: AsyncIO
Classifier: Programming Language :: Python :: 3
Classifier: Programming Language :: Python :: 3.6
Classifier: Programming Language :: Python :: 3.7
Classifier: Programming Language :: Python :: 3.8
Classifier: Programming Language :: Python :: 3.9
Classifier: Programming Language :: Python :: 3 :: Only
Requires-Python: >=3.6
Requires-Dist: ormar
Requires-Dist: sqlalchemy (<=1.3.23,>=1.3.18)
